notebookc/__init__.py
notebookc/notebookc.py
notebookc-0.0.5.dist-info/LICENSE
notebookc-0.0.5.dist-info/METADATA
notebookc-0.0.5.dist-info/WHEEL
notebookc-0.0.5.dist-info/top_level.txt
notebookc-0.0.5.dist-info/RECORD
